{
    "dark" : {
        "black_dark" : "#16181B",
        "black" : "#1b1e23",
        "black_light" : "#22262f",
        "grey_dark" : "#3B455A",
        "grey" : "#4f5b6e",
        "grey_light" : "#8a95aa",
        "white_dark" : "#dce1ec",
        "white_darker" : "#CAD2E2",
        "white" : "#F2F4F8",
        "white_light" : "#FBFCFF",
        "blue_light": "#7EA2F2",
        "blue": "#5C82E0",
        "blue_dark": "#4667C2",
        "yellow" : "#FFF275",
        "yellow_dark" : "#F0C808",
        "orange" : "#FF8C42",
        "rose_light" : "#F49FBC",
        "rose" : "#BC4E78",
        "rose_dark" : "#A13D63",
        "mint" : "#9DD9D2",
        "xanadu" : "#73877B",
        "emerald" : "#169873",
        "green_light" : "#99E000",
        "green" : "#75ab00",
        "green_dark" : "#628F00",
        "red_light" : "#EA4B48",
        "red" : "#E73936",
        "red_dark" : "#DB1D1A",
        "company_color1" : "#ffed29",
        "company_color2" : "#2720ad",
        "cyan" : "#00a8f4"
    }
}